byceps/__init__.py
byceps-0.0.3.dist-info/WHEEL
byceps-0.0.3.dist-info/entry_points.txt
byceps-0.0.3.dist-info/METADATA
byceps-0.0.3.dist-info/RECORD
