Metadata-Version: 2.3
Name: byceps
Version: 0.0.3
Summary: LAN party web platform
Keywords: lanparty
Author: Jochen Kupperschmidt
Author-email: Jochen Kupperschmidt <homework@nwsnet.de>
License: Revised BSD License
Classifier: Environment :: Web Environment
Classifier: Framework :: Flask
Classifier: Intended Audience :: Developers
Classifier: Intended Audience :: Other Audience
Classifier: License :: OSI Approved :: BSD License
Classifier: Natural Language :: English
Classifier: Natural Language :: German
Classifier: Programming Language :: JavaScript
Classifier: Programming Language :: Python
Classifier: Programming Language :: Python :: 3
Classifier: Programming Language :: Python :: 3.11
Classifier: Programming Language :: Python :: 3.12
Classifier: Programming Language :: Python :: 3.13
Classifier: Topic :: Communications
Classifier: Topic :: Games/Entertainment
Classifier: Topic :: Internet :: WWW/HTTP :: Dynamic Content :: Content Management System
Classifier: Topic :: Internet :: WWW/HTTP :: Dynamic Content :: Message Boards
Classifier: Topic :: Internet :: WWW/HTTP :: Dynamic Content :: News/Diary
Requires-Python: >=3.11
Project-URL: Documentation, https://byceps.readthedocs.io/
Project-URL: Homepage, https://byceps.nwsnet.de/
Project-URL: Repository, https://github.com/byceps/byceps
